bin/__init__.py
bin/run_app.py
proxmoxtemplates/__init__.py
proxmoxtemplates/main.py
proxmoxtemplates/proxmox_form.py
proxmoxtemplates/template_form.py
proxmoxtemplates/deployment_utils/__init__.py
proxmoxtemplates/deployment_utils/create_obj.py
proxmoxtemplates/deployment_utils/deployment.py
proxmoxtemplates/deployment_utils/file_handling.py
proxmoxtemplates/deployment_utils/templating.py
proxmoxtemplates/deployment_utils/deployment_template/files/99-pve.cfg
proxmoxtemplates/deployment_utils/deployment_template/http/meta-data
proxmoxtemplates/deployment_utils/deployment_template/jinja_templates/base_template.pkr.hcl.j2
proxmoxtemplates/deployment_utils/deployment_template/jinja_templates/user-data.j2
proxmoxtemplates/frontend_utils/__init__.py
proxmoxtemplates/frontend_utils/utils.py
proxmoxtemplates/proxmox_utils/__init__.py
proxmoxtemplates/proxmox_utils/utils.py
proxmoxtemplates-0.1.17.dist-info/METADATA
proxmoxtemplates-0.1.17.dist-info/WHEEL
proxmoxtemplates-0.1.17.dist-info/entry_points.txt
proxmoxtemplates-0.1.17.dist-info/top_level.txt
proxmoxtemplates-0.1.17.dist-info/RECORD
