Metadata-Version: 2.1
Name: proxmoxtemplates
Version: 0.1.17
Requires-Dist: streamlit ==1.34.0
Requires-Dist: proxmoxer ==2.0.1
Requires-Dist: pydantic ==2.7.1
Requires-Dist: jinja2 ==3.1.4
Requires-Dist: keyboard ==0.13.5
